CHANGELOG.md
csv_download/__init__.py
csv_download/main.py
csv_download-0.1.2.dist-info/entry_points.txt
csv_download-0.1.2.dist-info/LICENSE
csv_download-0.1.2.dist-info/WHEEL
csv_download-0.1.2.dist-info/METADATA
csv_download-0.1.2.dist-info/RECORD
