Metadata-Version: 2.1
Name: csv-download
Version: 0.1.2
Summary: Script to specify the column with URL in csv and download and save in bulk.
Home-page: https://github.com/Godan/csv_download
License: MIT
Author: godan
Author-email: shogo070920@gmail.com
Requires-Python: >=3.8,<4.0
Classifier: License :: OSI Approved :: MIT License
Classifier: Programming Language :: Python :: 3
Classifier: Programming Language :: Python :: 3.10
Classifier: Programming Language :: Python :: 3.8
Classifier: Programming Language :: Python :: 3.9
Project-URL: Repository, https://github.com/Godan/csv_download
